[
{
  "model": "wagtailcore.locale",
  "pk": 1,
  "fields": {
    "language_code": "en"
  }
},
{
  "model": "wagtailcore.site",
  "pk": 2,
  "fields": {
    "hostname": "localhost",
    "port": 80,
    "site_name": "",
    "root_page": 3,
    "is_default_site": true
  }
},
{
  "model": "wagtailcore.collection",
  "pk": 1,
  "fields": {
    "path": "0001",
    "depth": 1,
    "numchild": 0,
    "name": "Root"
  }
},
{
  "model": "wagtailcore.referenceindex",
  "pk": 1,
  "fields": {
    "content_type": [
      "wagtailimages",
      "image"
    ],
    "base_content_type": [
      "wagtailimages",
      "image"
    ],
    "object_id": "1",
    "to_content_type": [
      "wagtailcore",
      "collection"
    ],
    "to_object_id": "1",
    "model_path": "collection",
    "content_path": "collection",
    "content_path_hash": "b40b1263-e929-57f2-a7f8-9dbce56b887b"
  }
},
{
  "model": "wagtailcore.referenceindex",
  "pk": 4,
  "fields": {
    "content_type": [
      "blog",
      "blogpage"
    ],
    "base_content_type": [
      "wagtailcore",
      "page"
    ],
    "object_id": "10",
    "to_content_type": [
      "wagtailimages",
      "image"
    ],
    "to_object_id": "1",
    "model_path": "gallery_images.item.image",
    "content_path": "gallery_images.1.image",
    "content_path_hash": "43650d34-ff5a-57e1-8285-1d1a3528d2c8"
  }
},
{
  "model": "wagtailcore.referenceindex",
  "pk": 5,
  "fields": {
    "content_type": [
      "blog",
      "blogpage"
    ],
    "base_content_type": [
      "wagtailcore",
      "page"
    ],
    "object_id": "10",
    "to_content_type": [
      "taggit",
      "tag"
    ],
    "to_object_id": "1",
    "model_path": "tagged_items.item.tag",
    "content_path": "tagged_items.1.tag",
    "content_path_hash": "0a1d4af4-028a-541c-9ba8-bcfab5741d17"
  }
},
{
  "model": "wagtailcore.workflowpage",
  "pk": 1,
  "fields": {
    "workflow": 1
  }
},
{
  "model": "wagtailcore.workflowtask",
  "pk": 1,
  "fields": {
    "sort_order": 0,
    "workflow": 1,
    "task": 1
  }
},
{
  "model": "wagtailcore.task",
  "pk": 1,
  "fields": {
    "name": "Moderators approval",
    "content_type": [
      "wagtailcore",
      "groupapprovaltask"
    ],
    "active": true
  }
},
{
  "model": "wagtailcore.workflow",
  "pk": 1,
  "fields": {
    "name": "Moderators approval",
    "active": true
  }
},
{
  "model": "taggit.tag",
  "pk": 1,
  "fields": {
    "name": "cecd",
    "slug": "cecd"
  }
},
{
  "model": "auth.group",
  "pk": 1,
  "fields": {
    "name": "Moderators",
    "permissions": [
      [
        "access_admin",
        "wagtailadmin",
        "admin"
      ],
      [
        "add_document",
        "wagtaildocs",
        "document"
      ],
      [
        "change_document",
        "wagtaildocs",
        "document"
      ],
      [
        "choose_document",
        "wagtaildocs",
        "document"
      ],
      [
        "delete_document",
        "wagtaildocs",
        "document"
      ],
      [
        "add_image",
        "wagtailimages",
        "image"
      ],
      [
        "change_image",
        "wagtailimages",
        "image"
      ],
      [
        "delete_image",
        "wagtailimages",
        "image"
      ]
    ]
  }
},
{
  "model": "auth.group",
  "pk": 2,
  "fields": {
    "name": "Editors",
    "permissions": [
      [
        "access_admin",
        "wagtailadmin",
        "admin"
      ],
      [
        "add_document",
        "wagtaildocs",
        "document"
      ],
      [
        "change_document",
        "wagtaildocs",
        "document"
      ],
      [
        "choose_document",
        "wagtaildocs",
        "document"
      ],
      [
        "delete_document",
        "wagtaildocs",
        "document"
      ],
      [
        "add_image",
        "wagtailimages",
        "image"
      ],
      [
        "change_image",
        "wagtailimages",
        "image"
      ],
      [
        "delete_image",
        "wagtailimages",
        "image"
      ]
    ]
  }
},
{
  "model": "auth.user",
  "pk": 1,
  "fields": {
    "password": "pbkdf2_sha256$600000$Y5BNXICO7Xn4k99sqGLSVw$GvTb+HuxJkG0aJNWzm4V1H+WVE1CVrPoeCXJvc0okfE=",
    "last_login": "2023-05-22T19:00:55.380Z",
    "is_superuser": true,
    "username": "mo",
    "first_name": "",
    "last_name": "",
    "email": "",
    "is_staff": true,
    "is_active": true,
    "date_joined": "2023-05-22T18:59:34.511Z",
    "groups": [],
    "user_permissions": []
  }
},
{
  "model": "auth.user",
  "pk": 2,
  "fields": {
    "password": "pbkdf2_sha256$600000$aLMIenjBTstesfLBHp9NZC$pg6sVZifQqznffQn0kdWMGHWeHDhgVykKoLp2rxczQE=",
    "last_login": "2023-06-12T14:50:58.137Z",
    "is_superuser": true,
    "username": "mohamed",
    "first_name": "",
    "last_name": "",
    "email": "mderkaoui10@gmail.com",
    "is_staff": true,
    "is_active": true,
    "date_joined": "2023-06-12T09:06:17.026Z",
    "groups": [],
    "user_permissions": []
  }
},
{
  "model": "blog.blogpagetag",
  "pk": 1,
  "fields": {
    "tag": 1,
    "content_object": 10
  }
},
{
  "model": "blog.blogpage",
  "pk": 10,
  "fields": {
    "date": "2023-06-09",
    "intro": "cxs",
    "body": "<p data-block-key=\"fxdcs\">dsvsd</p>",
    "categories": []
  }
},
{
  "model": "blog.blogindexpage",
  "pk": 4,
  "fields": {
    "intro": ""
  }
},
{
  "model": "blog.blogpagegalleryimage",
  "pk": 1,
  "fields": {
    "sort_order": 0,
    "page": 10,
    "image": 1,
    "caption": ""
  }
},
{
  "model": "persona.personaindexpage",
  "pk": 5,
  "fields": {
    "intro": "<p data-block-key=\"ge0us\">Lista de mohamed</p>"
  }
},
{
  "model": "futbol.equipo",
  "pk": 8,
  "fields": {
    "nombre": "real madrid",
    "imagen": "images/p_13.png",
    "contenido": "<p data-block-key=\"7b13v\">Real Madrid Club de Fútbol, commonly referred to as Real Madrid, is one of the most successful and popular football (soccer) clubs in the world. Based in Madrid, Spain, Real Madrid was founded in 1902 and has since become a symbol of Spanish football excellence.</p><p data-block-key=\"9golf\"></p><p data-block-key=\"f3e8t\">Achievements:</p><p data-block-key=\"au3fj\">Real Madrid has an illustrious history and a record of success both domestically and internationally. They have won the prestigious UEFA Champions League a record 13 times, with their most recent victories coming in the years 2014, 2016, 2017, 2018, and 2022. Real Madrid has also won numerous domestic league titles, with their most recent La Liga championship coming in the 2021-2022 season.</p><p data-block-key=\"e4maf\"></p><p data-block-key=\"djh6h\">Stadium:</p><p data-block-key=\"7odjm\">Real Madrid plays its home matches at the Santiago Bernabéu Stadium, which has a seating capacity of over 81,000 spectators. The stadium is located in the Chamartín district of Madrid and is one of the most iconic football venues in the world.</p><p data-block-key=\"5ihul\"></p><p data-block-key=\"4u438\">Rivalries:</p><p data-block-key=\"fr4g7\">Real Madrid has a fierce rivalry with Barcelona, known as &quot;El Clásico.&quot; Matches between these two clubs are highly anticipated and attract global attention. The rivalry is not only based on football but also has historical and cultural roots, representing the different identities of the cities of Madrid and Barcelona.</p><p data-block-key=\"31ac1\"></p><p data-block-key=\"e26m6\">Notable Players:</p><p data-block-key=\"67jk9\">Real Madrid has had many legendary players don the white jersey over the years. Some of the notable players who have represented the club include Alfredo Di Stéfano, Ferenc Puskás, Cristiano Ronaldo, Zinedine Zidane, Raúl González, Iker Casillas, Sergio Ramos, and many more.</p><p data-block-key=\"9nc2c\"></p><p data-block-key=\"3s887\">Current Situation (as of September 2021):</p><p data-block-key=\"10nqr\">Please note that as an AI model, I don&#x27;t have access to real-time information. As of my last knowledge update in September 2021, Real Madrid was still considered one of the top clubs in European football. However, the specific details about the current squad, performance, or any recent developments are beyond my knowledge cutoff. To get the most accurate and up-to-date information, I recommend referring to official sports news sources or the club&#x27;s official website.</p>"
  }
},
{
  "model": "futbol.equipo",
  "pk": 9,
  "fields": {
    "nombre": "Fútbol Club Barcelona",
    "imagen": "images/varça.png",
    "contenido": ""
  }
},
{
  "model": "futbol.equipo",
  "pk": 11,
  "fields": {
    "nombre": "artetico de Madrid",
    "imagen": "images/p_3.png",
    "contenido": "<p data-block-key=\"bdma3\"> </p><p data-block-key=\"78t8l\">El Atlético de Madrid, también conocido como Atlético, es un club de fútbol español con sede en Madrid. Fue fundado en 1903 y desde entonces ha sido uno de los clubes más exitosos de España y Europa.</p><p data-block-key=\"clc9j\">El Atlético de Madrid ha ganado numerosos títulos a lo largo de su historia, incluyendo la Liga española en varias ocasiones, la Copa del Rey, la Supercopa de España y la Liga Europa de la UEFA. Además, ha alcanzado la final de la Liga de Campeones de la UEFA en varias ocasiones, siendo subcampeón en 1974, 2014 y 2016.</p><p data-block-key=\"37ncn\">El equipo disputa sus partidos como local en el Estadio Wanda Metropolitano, con capacidad para más de 67,000 espectadores. Sus colores distintivos son el rojo y el blanco, y su apodo es &quot;los colchoneros&quot; en referencia a los colchones que se vendían en la antigua ubicación del estadio.</p><p data-block-key=\"dfepi\">A lo largo de su historia, el Atlético de Madrid ha tenido jugadores icónicos como Luis Aragonés, Fernando Torres, Diego Godín y Antoine Griezmann, entre otros. El club cuenta con una gran base de seguidores y tiene una intensa rivalidad con el Real Madrid y el FC Barcelona, conocida como el &quot;Derbi madrileño&quot; y el &quot;Derbi español&quot;, respectivamente.</p><p data-block-key=\"4ljn5\">En resumen, el Atlético de Madrid es uno de los clubes más destacados de España, con una historia rica en éxitos y una base de seguidores apasionados.</p>"
  }
},
{
  "model": "futbol.equipo",
  "pk": 12,
  "fields": {
    "nombre": "Real Sociedad de Fútbol",
    "imagen": "images/p_14.png",
    "contenido": "<p data-block-key=\"13ba8\">Real Sociedad de Fútbol, commonly referred to as Real Sociedad or simply La Real, is a professional football club based in San Sebastián, Spain. The club was founded on September 7, 1909, and has since become one of the most successful and iconic clubs in Spanish football.</p><p data-block-key=\"1kbfl\"></p><p data-block-key=\"7ni0t\">Real Sociedad has a strong history and tradition. They have spent the majority of their existence in La Liga, the top tier of Spanish football. The club has won the La Liga title on two occasions, in the 1980-81 and 2020-21 seasons, establishing themselves as a force to be reckoned with.</p><p data-block-key=\"89b2p\"></p><p data-block-key=\"agju4\">The team plays its home matches at the Anoeta Stadium, which has a seating capacity of over 39,000 spectators. The club&#x27;s colors are blue and white, and their nickname is &quot;Txuri-urdin,&quot; which means &quot;White and Blue&quot; in Basque, reflecting their regional identity.</p><p data-block-key=\"5v702\"></p><p data-block-key=\"dv9d6\">Real Sociedad has a passionate fan base and enjoys a strong rivalry with Athletic Bilbao, another prominent Basque club. Matches between the two teams are known as the Basque derby or &quot;Derbi Vasco,&quot; and they are always highly anticipated and fiercely contested.</p><p data-block-key=\"1aup5\"></p><p data-block-key=\"b08is\">Over the years, Real Sociedad has produced and developed many talented players, some of whom have gone on to achieve success both domestically and internationally. Notable players associated with the club include Xabi Alonso, Darko Kovacevic, Antoine Griezmann, and current captain Mikel Oyarzabal.</p><p data-block-key=\"91luc\"></p><p data-block-key=\"6piak\">Real Sociedad has also achieved success in European competitions. They have participated in the UEFA Champions League and UEFA Europa League, reaching the semifinals of the latter in the 2020-21 season.</p><p data-block-key=\"99qc6\"></p><p data-block-key=\"6l1l\">The club places significant emphasis on youth development and has a renowned youth academy known as &quot;Zubieta,&quot; which has produced numerous talented players who have gone on to represent both the club and the national team.</p><p data-block-key=\"4vu5r\"></p><p data-block-key=\"eta57\">Overall, Real Sociedad de Fútbol is a storied club with a rich history, a dedicated fan base, and a commitment to developing young talent. They continue to compete at the highest level of Spanish football, aiming to achieve further success both domestically and in European competitions.Real Sociedad de Fútbol, commonly referred to as Real Sociedad or simply La Real, is a professional football club based in San Sebastián, Spain. The club was founded on September 7, 1909, and has since become one of the most successful and iconic clubs in Spanish football.</p><p data-block-key=\"fb9ff\"></p><p data-block-key=\"c88n8\">Real Sociedad has a strong history and tradition. They have spent the majority of their existence in La Liga, the top tier of Spanish football. The club has won the La Liga title on two occasions, in the 1980-81 and 2020-21 seasons, establishing themselves as a force to be reckoned with.</p><p data-block-key=\"60n4a\"></p><p data-block-key=\"e20sd\">The team plays its home matches at the Anoeta Stadium, which has a seating capacity of over 39,000 spectators. The club&#x27;s colors are blue and white, and their nickname is &quot;Txuri-urdin,&quot; which means &quot;White and Blue&quot; in Basque, reflecting their regional identity.</p><p data-block-key=\"dmplh\"></p><p data-block-key=\"5j2gg\">Real Sociedad has a passionate fan base and enjoys a strong rivalry with Athletic Bilbao, another prominent Basque club. Matches between the two teams are known as the Basque derby or &quot;Derbi Vasco,&quot; and they are always highly anticipated and fiercely contested.</p><p data-block-key=\"cntju\"></p><p data-block-key=\"60ieh\">Over the years, Real Sociedad has produced and developed many talented players, some of whom have gone on to achieve success both domestically and internationally. Notable players associated with the club include Xabi Alonso, Darko Kovacevic, Antoine Griezmann, and current captain Mikel Oyarzabal.</p><p data-block-key=\"aoni4\"></p><p data-block-key=\"6g1\">Real Sociedad has also achieved success in European competitions. They have participated in the UEFA Champions League and UEFA Europa League, reaching the semifinals of the latter in the 2020-21 season.</p><p data-block-key=\"a6gfi\"></p><p data-block-key=\"1qm2f\">The club places significant emphasis on youth development and has a renowned youth academy known as &quot;Zubieta,&quot; which has produced numerous talented players who have gone on to represent both the club and the national team.</p><p data-block-key=\"243lt\"></p><p data-block-key=\"f7t5h\">Overall, Real Sociedad de Fútbol is a storied club with a rich history, a dedicated fan base, and a commitment to developing young talent. They continue to compete at the highest level of Spanish football, aiming to achieve further success both domestically and in European competitions.Real Sociedad de Fútbol, commonly referred to as Real Sociedad or simply La Real, is a professional football club based in San Sebastián, Spain. The club was founded on September 7, 1909, and has since become one of the most successful and iconic clubs in Spanish football.</p><p data-block-key=\"dtdn4\"></p><p data-block-key=\"dp6rh\">Real Sociedad has a strong history and tradition. They have spent the majority of their existence in La Liga, the top tier of Spanish football. The club has won the La Liga title on two occasions, in the 1980-81 and 2020-21 seasons, establishing themselves as a force to be reckoned with.</p><p data-block-key=\"ah2p5\"></p><p data-block-key=\"2s8c6\">The team plays its home matches at the Anoeta Stadium, which has a seating capacity of over 39,000 spectators. The club&#x27;s colors are blue and white, and their nickname is &quot;Txuri-urdin,&quot; which means &quot;White and Blue&quot; in Basque, reflecting their regional identity.</p><p data-block-key=\"ehgn6\"></p><p data-block-key=\"7n9np\">Real Sociedad has a passionate fan base and enjoys a strong rivalry with Athletic Bilbao, another prominent Basque club. Matches between the two teams are known as the Basque derby or &quot;Derbi Vasco,&quot; and they are always highly anticipated and fiercely contested.</p><p data-block-key=\"4vrvn\"></p><p data-block-key=\"5q2qc\">Over the years, Real Sociedad has produced and developed many talented players, some of whom have gone on to achieve success both domestically and internationally. Notable players associated with the club include Xabi Alonso, Darko Kovacevic, Antoine Griezmann, and current captain Mikel Oyarzabal.</p><p data-block-key=\"c6vv1\"></p><p data-block-key=\"1ve0b\">Real Sociedad has also achieved success in European competitions. They have participated in the UEFA Champions League and UEFA Europa League, reaching the semifinals of the latter in the 2020-21 season.</p><p data-block-key=\"f8g6e\"></p><p data-block-key=\"ckp1e\">The club places significant emphasis on youth development and has a renowned youth academy known as &quot;Zubieta,&quot; which has produced numerous talented players who have gone on to represent both the club and the national team.</p><p data-block-key=\"3nrb2\"></p><p data-block-key=\"3rp3r\">Overall, Real Sociedad de Fútbol is a storied club with a rich history, a dedicated fan base, and a commitment to developing young talent. They continue to compete at the highest level of Spanish football, aiming to achieve further success both domestically and in European competitions.</p>"
  }
},
{
  "model": "futbol.equipo",
  "pk": 13,
  "fields": {
    "nombre": "Villarreal Club de Fútbol",
    "imagen": "images/p_20.png",
    "contenido": 